MI_AG/__init__.py
MI_AG-0.9.0.dist-info/LICENSE
MI_AG-0.9.0.dist-info/METADATA
MI_AG-0.9.0.dist-info/WHEEL
MI_AG-0.9.0.dist-info/top_level.txt
MI_AG-0.9.0.dist-info/RECORD
