Metadata-Version: 2.1
Name: MI-AG
Version: 0.9.0
Summary: Use mutual information and accelerated gradient method to filter out and optimize nonconvex sparse learning problems on large genetic data based on bed/bim/fam. Multiprocessing is now available.
Author-email: Kai Yang <kai.yang2@mail.mcgill.ca>
License: GNU AFFERO GENERAL PUBLIC LICENSE
Project-URL: Homepage, https://github.com/Kaiyangshi-Ito/MI_AG
Project-URL: Bug Tracker, https://github.com/Kaiyangshi-Ito/MI_AG/issues
Classifier: Programming Language :: Python :: 3
Classifier: License :: OSI Approved :: GNU Affero General Public License v3 or later (AGPLv3+)
Classifier: Operating System :: OS Independent
Requires-Python: >=3.7
License-File: LICENSE
